正解：C

レコードのコンパクトコンストラクタに関する問題です。自動的に生成される標準コンストラクタには、渡されてきた引数の妥当性を検証する機能はありません。そのような機能を追加したい場合には、コンパクトコンストラクタを使います。コンパクトコンストラクタは、次のようにレコード名だけで宣言するメソッドです。

例　コンパクトコンストラクタの宣言

```java
import java.util.Objects;

public record Customer(String name, int age, String address) {
    public Customer {
        if (Objects.isNull(name) || name.isBlank()) {
            throw new IllegalArgumentException();
        }
        if (age < 0) {
            throw new IllegalArgumentException();
        }
        if (Objects.isNull(address) || address.isBlank()) {
            throw new IllegalArgumentException();
        }
    }
}

```

このようなコンパクトコンストラクタを用意することで、自動的に生成される標準コンストラクタでフィールドに引数の値を代入する前に、その値の妥当性を検証することが可能です。上記のコードであれば、名前や住所がnullや空文字でないか、年齢がマイナスの値になっていないかなどの検証を行い、違反があれば例外をスローするように実装しています。このようなコンパクトコンストラクタを用意すれば、不正な値を扱うことがなくなり、安心してデータキャリアとして使うことができます。

コンパクトコンストラクタは、コンパイルすると標準コンストラクタに付け

加える処理を記述するものですが、コンパイルされたクラスファイルをjavapコマンドで逆コンパイルすると、標準コンストラクタとコンパクトコンストラクタの関係がよくわかります。たとえば、次のようなレコードがあったとします。このレコードには単純な処理のコンパクトコンストラクタだけを追加しておきます。

例　標準コンストラクタとコンパクトコンストラクタの関係を調べるためのコード

```java
public record Customer(String name, int age, String address) {
    public Customer {
        System.out.println(name);
    }
}

```

このレコードをコンパイルし、クラスファイルをjavapコマンドで逆コンパイルすると、次のような結果を得られます。

例　javapコマンドの実行結果

```text
> javap -c Customer
public final class Customer extends java.lang.Record {
  public Customer(java.lang.String, int, java.lang.String);
    Code:
       0: aload_0
       1: invokespecial #13                 // Method java/lang/Record."<init>":()V
       4: getstatic     #16                 // Field java/lang/System.out:Ljava/io/PrintStream;
       7: aload_1
       8: invokevirtual #22                 // Method java/io/PrintStream.println:(Ljava/lang/String;)V
      11: aload_0
      12: aload_3
      13: putfield      #28                 // Field address:Ljava/lang/String;
      16: aload_0
      17: iload_2
      18: putfield      #30                 // Field age:I
      21: aload_0
      22: aload_1
      23: putfield      #32                 // Field name:Ljava/lang/String;
      26: return
  ...省略...
}

```

javapコマンドの実行結果から、コンストラクタでは、コンパクトコンストラクタの処理（4〜8）が実行されてから、各フィールドが初期化する標準コンストラクタ内の処理（11〜23）が実行されていることがわかります。

コンパクトコンストラクタには次のようなルールがあります。これらのルールに反した場合は、コンパイルエラーになります。

・コンストラクタ内にreturnを記述してはならない
・明示的に別のコンストラクタ呼び出しをしてはならない
・フィールドにアクセスしてはならない
・コンパクトコンストラクタは1つしか宣言できない

コンパクトコンストラクタは、前述のようにコンパイルされることで標準コンストラクタと組み合わさって1つのコンストラクタになります。そのため、まだ標準コンストラクタの処理が終わっていないにもかかわらず、コンパクトコンストラクタ内でreturnされてしまうとフィールドの初期化ができないままのインスタンスができあがってしまいます。

また、別のコンストラクタ呼び出しを禁止しているのは、コンパクトコンストラクタが標準コンストラクタと組み合わさって1つのコンストラクタになることに由来します。前問の解説で学んだように、レコードではコンストラクタをオーバーロードして複数定義することが可能ですが、そのときにはオーバーロードしたコンストラクタの先頭行で標準コンストラクタを呼び出さなければいけませんでした。コンパクトコンストラクタ内で、別のコンストラクタを呼び出してしまうと、そのコンストラクタから標準コンストラクタが呼び出されるうえに、さらにコンパクトコンストラクタと標準コンストラクタが組み合わさるわけですから、2回も標準コンストラクタが呼び出されることになってしまいます。

コンパクトコンストラクタ内でフィールドにアクセスできないのは、フィールドの初期化は標準コンストラクタ内で実施するものだからです。コンパクトコンストラクタと標準コンストラクタは組み合わさって1つのコンストラクタになりますが、その順番はコンパクトコンストラクタの次に標準コンストラクタです。そのため、コンパクトコンストラクタの処理を実行しているタイミングでは、まだフィールドが初期化されないのです。次のコードは、レコードがコンパイルされ、コンパクトコンストラクタと標準コンストラクタが組み合わさったコンストラクタをイメージしてもらうためのものです。

例　コンパクトコンストラクタが処理される位置

```java
public class Customer {

    private String name;
    private int age;
    private String address;

    public Customer(String name, int age, String address) {

        // Compact Constructor

        this.name = name;
        this.age = age;
        this.address = address;
    }
}

```

このように、コンパクトコンストラクタの処理はフィールドの初期化より先に実行されます。また、コンストラクタの引数とフィールド名が同じなので、this参照（this.xxx）を使わなければフィールドではなく、コンストラクタの引数にアクセスすることになる点も注意してください。
コンパクトコンストラクタでは、this参照（this.xxx）を使ってフィールドにアクセスすることもできません。コンパクトコンストラクタの処理が実行されているタイミングでは、まだフィールドの初期化が終わっていません。そのため、フィールドの値を参照するようなコードはコンパイルエラーになります。また、フィールドの値をこのタイミングで初期化してしまうと、その後で続く標準コンストラクタの処理ができなくなってしまいます。

最後に、コンパクトコンストラクタは標準コンストラクタと組み合わせるためのものです。そのため、複数のコンパクトコンストラクタがあるとどれと組み合わせてよいのかがわかりません。そのため、コンパクトコンストラクタは1つしか定義できません。たとえば、次のように2つのコンパクトコンストラクタを持つレコードを用意します。

例　2つのコンパクトコンストラクタを定義（コンパイルエラー）

```java
public record Customer(String name, int age, String address) {
    public Customer {
        System.out.println("A");
    }
    public Customer {
        System.out.println("B");
    }
}

```

このコードをコンパイルすると、次のようにコンパイルエラーが発生します。

例　コンパイルエラーになる

```text
> javac Customer.java
Customer.java:5: エラー: コンストラクタ Customer(String,int,String)はすでにレコードCustomerで定義されています
    public Customer {
    ^
エラー1個

```

設問のコードでは、コンパクトコンストラクタ内でthis参照を使ってフィールドの値を利用しています。しかし、コンパクトコンストラクタが実行されるタイミングでは、まだフィールドの値は初期化されていません。よって、このコードはコンパイルエラーになります。以上のことから、選択肢Cが正解です。

試験対策

コンパクトコンストラクタの構文は、レコード名のみ宣言するものです。引数そのものの宣言はないので注意しましょう。

参考

コンパクトコンストラクタは、引数の検証だけでなく、標準コンストラクタでは実現されない初期化に関するロジックを実装したりすることにも使えます。代替コンストラクタとの違いは、フィールドの初期化がされる前か後かの違いです。フィールドの初期化がされる前に実行したい初期化処理があればコンパクトコンストラクタを使いましょう。
